iotile_transport_native_ble/__init__.py
iotile_transport_native_ble/config_variables.py
iotile_transport_native_ble/connection_manager.py
iotile_transport_native_ble/device_adapter.py
iotile_transport_native_ble/tilebus.py
iotile_transport_native_ble/virtual_ble.py
iotile_transport_native_ble-3.1.0.dist-info/LICENSE.md
iotile_transport_native_ble-3.1.0.dist-info/METADATA
iotile_transport_native_ble-3.1.0.dist-info/WHEEL
iotile_transport_native_ble-3.1.0.dist-info/entry_points.txt
iotile_transport_native_ble-3.1.0.dist-info/top_level.txt
iotile_transport_native_ble-3.1.0.dist-info/RECORD
